Metadata-Version: 1.1
Name: django-oauth-toolkit-scopes-backend
Version: 0.11.0
Summary: OAuth2 goodies for Django
Home-page: https://github.com/TransparentHealth/django-oauth-toolkit
Author: Federico Frenguelli, Massimiliano Pippi, Alan Viars
Author-email: synasius@gmail.com, mpippi@gmail.com
License: BSD
Keywords: django oauth oauth2 oauthlib
Platform: UNKNOWN
Classifier: Development Status :: 4 - Beta
Classifier: Environment :: Web Environment
Classifier: Framework :: Django
Classifier: License :: OSI Approved :: BSD License
Classifier: Operating System :: OS Independent
Classifier: Programming Language :: Python :: 3.4
Classifier: Programming Language :: Python :: 3.5
Classifier: Topic :: Software Development :: Libraries :: Python Modules
Classifier: Framework :: Django
Classifier: Framework :: Django :: 2.1
